<?xml version="1.0"?>
<MadHatterBot xmlns:xsi="http://www.w3.org/2001/XMLSchema-instance" xmlns:xsd="http://www.w3.org/2001/XMLSchema">
  <BotType>MadHatterBot</BotType>
  <MessageProfile xsi:type="SimpleCustomBotProfile">
    <TradeAmountErrors>true</TradeAmountErrors>
    <Activation>true</Activation>
    <OrderExecution>false</OrderExecution>
    <PositionSwitch>true</PositionSwitch>
  </MessageProfile>
  <IsBacktesting>false</IsBacktesting>
  <GUID>912b7c6a-4498-41ef-8f47-03aaf00f646f</GUID>
  <Name>P: BTS 56 wow</Name>
  <AccountId>ddc2187b-da39-49b0-bfac-a507cf91385c</AccountId>
  <PriceMarket>
    <PriceSource>21</PriceSource>
    <ContractName />
    <PrimaryCurrency>BTS</PrimaryCurrency>
    <SecondaryCurrency>BTC</SecondaryCurrency>
  </PriceMarket>
  <Leverage>1</Leverage>
  <CurrentFeePercentage>0.1</CurrentFeePercentage>
  <SettlementDate>0</SettlementDate>
  <ProfitLabel>BTC</ProfitLabel>
  <Activated>false</Activated>
  <ActivatedSince>1527117618</ActivatedSince>
  <DeactivatedSince>1527463218</DeactivatedSince>
  <StatusPriceSourceOk>true</StatusPriceSourceOk>
  <StatusAccountOk>true</StatusAccountOk>
  <OpenOrdersOk>true</OpenOrdersOk>
  <WalletOk>true</WalletOk>
  <OpenOrderId />
  <TotalFeeCosts>0.000611460</TotalFeeCosts>
  <TotalProfits>0.00063000</TotalProfits>
  <ROI>0.0630</ROI>
  <LastPriceUpdate>0.00002944</LastPriceUpdate>
  <ContractValue>1</ContractValue>
  <LastUpdateTime>1527975991</LastUpdateTime>
  <GroupName>5656ee26-a1f9-4544-a1f0-41cac36a9c40</GroupName>
  <Notes />
  <CustomTemplate>LOCKEDLIMITORDERGUID</CustomTemplate>
  <BotLogBook>
    <string>6/2/2018 11:46:31 PM Trade amount is OK (max 44088.921875 BTS)</string>
    <string>6/2/2018 11:46:31 PM Bot settings saved.</string>
  </BotLogBook>
  <CompletedOrders>
    <BaseOrder xsi:type="ExchangeOrder">
      <OrderId>3694627e-12c5-43a8-978d-6595a0984f31</OrderId>
      <OrderStatus>Completed</OrderStatus>
      <OrderStatusAsString>Completed</OrderStatusAsString>
      <OrderType>Buy</OrderType>
      <OrderTypeAsString>Buy</OrderTypeAsString>
      <PriceType>Limit</PriceType>
      <PriceTypeAsString>Limit</PriceTypeAsString>
      <Amount>1000</Amount>
      <AmountFilled>0.0</AmountFilled>
      <Price>0.00002567</Price>
      <FeePercentage>0.1</FeePercentage>
      <FeeCosts>0.000025670</FeeCosts>
      <Profits>0.0</Profits>
      <Notes />
      <Origin />
      <DependsOn />
      <IsExecutingAsId />
      <AddedTime>2018-05-23T23:50:00</AddedTime>
      <UnixAddedTime>1527119400</UnixAddedTime>
      <LastUpdate>2018-05-23T23:50:00</LastUpdate>
      <UnixLastUpdate>1527119400</UnixLastUpdate>
      <TimeoutInMinutes>15</TimeoutInMinutes>
      <Platform>Sandbox</Platform>
      <Pair>
        <PrimaryCurrency>BTS</PrimaryCurrency>
        <SecondaryCurrency>BTC</SecondaryCurrency>
      </Pair>
    </BaseOrder>
    <BaseOrder xsi:type="ExchangeOrder">
      <OrderId>bbcd5c5a-266e-45fd-a460-96e2d93ec9b6</OrderId>
      <OrderStatus>Completed</OrderStatus>
      <OrderStatusAsString>Completed</OrderStatusAsString>
      <OrderType>Sell</OrderType>
      <OrderTypeAsString>Sell</OrderTypeAsString>
      <PriceType>Limit</PriceType>
      <PriceTypeAsString>Limit</PriceTypeAsString>
      <Amount>1000</Amount>
      <AmountFilled>0.0</AmountFilled>
      <Price>0.00002663</Price>
      <FeePercentage>0.1</FeePercentage>
      <FeeCosts>0.000026630</FeeCosts>
      <Profits>0.00096000</Profits>
      <Notes />
      <Origin />
      <DependsOn />
      <IsExecutingAsId />
      <AddedTime>2018-05-24T02:55:00</AddedTime>
      <UnixAddedTime>1527130500</UnixAddedTime>
      <LastUpdate>2018-05-24T02:55:00</LastUpdate>
      <UnixLastUpdate>1527130500</UnixLastUpdate>
      <TimeoutInMinutes>15</TimeoutInMinutes>
      <Platform>Sandbox</Platform>
      <Pair>
        <PrimaryCurrency>BTS</PrimaryCurrency>
        <SecondaryCurrency>BTC</SecondaryCurrency>
      </Pair>
    </BaseOrder>
    <BaseOrder xsi:type="ExchangeOrder">
      <OrderId>436b526c-2f23-45ed-83fb-19c643cb7832</OrderId>
      <OrderStatus>Completed</OrderStatus>
      <OrderStatusAsString>Completed</OrderStatusAsString>
      <OrderType>Buy</OrderType>
      <OrderTypeAsString>Buy</OrderTypeAsString>
      <PriceType>Limit</PriceType>
      <PriceTypeAsString>Limit</PriceTypeAsString>
      <Amount>1000</Amount>
      <AmountFilled>0.0</AmountFilled>
      <Price>0.00002635</Price>
      <FeePercentage>0.1</FeePercentage>
      <FeeCosts>0.000026350</FeeCosts>
      <Profits>0.0</Profits>
      <Notes />
      <Origin />
      <DependsOn />
      <IsExecutingAsId />
      <AddedTime>2018-05-24T07:15:00</AddedTime>
      <UnixAddedTime>1527146100</UnixAddedTime>
      <LastUpdate>2018-05-24T07:15:00</LastUpdate>
      <UnixLastUpdate>1527146100</UnixLastUpdate>
      <TimeoutInMinutes>15</TimeoutInMinutes>
      <Platform>Sandbox</Platform>
      <Pair>
        <PrimaryCurrency>BTS</PrimaryCurrency>
        <SecondaryCurrency>BTC</SecondaryCurrency>
      </Pair>
    </BaseOrder>
    <BaseOrder xsi:type="ExchangeOrder">
      <OrderId>f1e96a83-8a9c-4f8f-a73f-63f3c771a7a0</OrderId>
      <OrderStatus>Completed</OrderStatus>
      <OrderStatusAsString>Completed</OrderStatusAsString>
      <OrderType>Sell</OrderType>
      <OrderTypeAsString>Sell</OrderTypeAsString>
      <PriceType>Limit</PriceType>
      <PriceTypeAsString>Limit</PriceTypeAsString>
      <Amount>1000</Amount>
      <AmountFilled>0.0</AmountFilled>
      <Price>0.00002568</Price>
      <FeePercentage>0.1</FeePercentage>
      <FeeCosts>0.000025680</FeeCosts>
      <Profits>-0.00067000</Profits>
      <Notes />
      <Origin />
      <DependsOn />
      <IsExecutingAsId />
      <AddedTime>2018-05-24T12:15:00</AddedTime>
      <UnixAddedTime>1527164100</UnixAddedTime>
      <LastUpdate>2018-05-24T12:15:00</LastUpdate>
      <UnixLastUpdate>1527164100</UnixLastUpdate>
      <TimeoutInMinutes>15</TimeoutInMinutes>
      <Platform>Sandbox</Platform>
      <Pair>
        <PrimaryCurrency>BTS</PrimaryCurrency>
        <SecondaryCurrency>BTC</SecondaryCurrency>
      </Pair>
    </BaseOrder>
    <BaseOrder xsi:type="ExchangeOrder">
      <OrderId>5459d90a-9633-4370-b9d1-389136d60f4e</OrderId>
      <OrderStatus>Completed</OrderStatus>
      <OrderStatusAsString>Completed</OrderStatusAsString>
      <OrderType>Buy</OrderType>
      <OrderTypeAsString>Buy</OrderTypeAsString>
      <PriceType>Limit</PriceType>
      <PriceTypeAsString>Limit</PriceTypeAsString>
      <Amount>1000</Amount>
      <AmountFilled>0.0</AmountFilled>
      <Price>0.00002685</Price>
      <FeePercentage>0.1</FeePercentage>
      <FeeCosts>0.000026850</FeeCosts>
      <Profits>0.0</Profits>
      <Notes />
      <Origin />
      <DependsOn />
      <IsExecutingAsId />
      <AddedTime>2018-05-24T21:00:00</AddedTime>
      <UnixAddedTime>1527195600</UnixAddedTime>
      <LastUpdate>2018-05-24T21:00:00</LastUpdate>
      <UnixLastUpdate>1527195600</UnixLastUpdate>
      <TimeoutInMinutes>15</TimeoutInMinutes>
      <Platform>Sandbox</Platform>
      <Pair>
        <PrimaryCurrency>BTS</PrimaryCurrency>
        <SecondaryCurrency>BTC</SecondaryCurrency>
      </Pair>
    </BaseOrder>
    <BaseOrder xsi:type="ExchangeOrder">
      <OrderId>b2806128-22fb-438a-b4c4-ef02f550f180</OrderId>
      <OrderStatus>Completed</OrderStatus>
      <OrderStatusAsString>Completed</OrderStatusAsString>
      <OrderType>Sell</OrderType>
      <OrderTypeAsString>Sell</OrderTypeAsString>
      <PriceType>Limit</PriceType>
      <PriceTypeAsString>Limit</PriceTypeAsString>
      <Amount>1000</Amount>
      <AmountFilled>0.0</AmountFilled>
      <Price>0.00002685</Price>
      <FeePercentage>0.1</FeePercentage>
      <FeeCosts>0.000026850</FeeCosts>
      <Profits>0.00000000</Profits>
      <Notes />
      <Origin />
      <DependsOn />
      <IsExecutingAsId />
      <AddedTime>2018-05-24T21:30:00</AddedTime>
      <UnixAddedTime>1527197400</UnixAddedTime>
      <LastUpdate>2018-05-24T21:30:00</LastUpdate>
      <UnixLastUpdate>1527197400</UnixLastUpdate>
      <TimeoutInMinutes>15</TimeoutInMinutes>
      <Platform>Sandbox</Platform>
      <Pair>
        <PrimaryCurrency>BTS</PrimaryCurrency>
        <SecondaryCurrency>BTC</SecondaryCurrency>
      </Pair>
    </BaseOrder>
    <BaseOrder xsi:type="ExchangeOrder">
      <OrderId>bd92999a-af1c-408b-8cbd-5eb05079206a</OrderId>
      <OrderStatus>Completed</OrderStatus>
      <OrderStatusAsString>Completed</OrderStatusAsString>
      <OrderType>Buy</OrderType>
      <OrderTypeAsString>Buy</OrderTypeAsString>
      <PriceType>Limit</PriceType>
      <PriceTypeAsString>Limit</PriceTypeAsString>
      <Amount>1000</Amount>
      <AmountFilled>0.0</AmountFilled>
      <Price>0.00002685</Price>
      <FeePercentage>0.1</FeePercentage>
      <FeeCosts>0.000026850</FeeCosts>
      <Profits>0.0</Profits>
      <Notes />
      <Origin />
      <DependsOn />
      <IsExecutingAsId />
      <AddedTime>2018-05-25T01:05:00</AddedTime>
      <UnixAddedTime>1527210300</UnixAddedTime>
      <LastUpdate>2018-05-25T01:05:00</LastUpdate>
      <UnixLastUpdate>1527210300</UnixLastUpdate>
      <TimeoutInMinutes>15</TimeoutInMinutes>
      <Platform>Sandbox</Platform>
      <Pair>
        <PrimaryCurrency>BTS</PrimaryCurrency>
        <SecondaryCurrency>BTC</SecondaryCurrency>
      </Pair>
    </BaseOrder>
    <BaseOrder xsi:type="ExchangeOrder">
      <OrderId>a30b0626-cb06-440f-a761-6a45c7a99882</OrderId>
      <OrderStatus>Completed</OrderStatus>
      <OrderStatusAsString>Completed</OrderStatusAsString>
      <OrderType>Sell</OrderType>
      <OrderTypeAsString>Sell</OrderTypeAsString>
      <PriceType>Limit</PriceType>
      <PriceTypeAsString>Limit</PriceTypeAsString>
      <Amount>1000</Amount>
      <AmountFilled>0.0</AmountFilled>
      <Price>0.00002696</Price>
      <FeePercentage>0.1</FeePercentage>
      <FeeCosts>0.000026960</FeeCosts>
      <Profits>0.00011000</Profits>
      <Notes />
      <Origin />
      <DependsOn />
      <IsExecutingAsId />
      <AddedTime>2018-05-25T03:50:00</AddedTime>
      <UnixAddedTime>1527220200</UnixAddedTime>
      <LastUpdate>2018-05-25T03:50:00</LastUpdate>
      <UnixLastUpdate>1527220200</UnixLastUpdate>
      <TimeoutInMinutes>15</TimeoutInMinutes>
      <Platform>Sandbox</Platform>
      <Pair>
        <PrimaryCurrency>BTS</PrimaryCurrency>
        <SecondaryCurrency>BTC</SecondaryCurrency>
      </Pair>
    </BaseOrder>
    <BaseOrder xsi:type="ExchangeOrder">
      <OrderId>59dcb8aa-300e-4caa-b9f7-69616e6d2a6c</OrderId>
      <OrderStatus>Completed</OrderStatus>
      <OrderStatusAsString>Completed</OrderStatusAsString>
      <OrderType>Buy</OrderType>
      <OrderTypeAsString>Buy</OrderTypeAsString>
      <PriceType>Limit</PriceType>
      <PriceTypeAsString>Limit</PriceTypeAsString>
      <Amount>1000</Amount>
      <AmountFilled>0.0</AmountFilled>
      <Price>0.0000266</Price>
      <FeePercentage>0.1</FeePercentage>
      <FeeCosts>0.00002660</FeeCosts>
      <Profits>0.0</Profits>
      <Notes />
      <Origin />
      <DependsOn />
      <IsExecutingAsId />
      <AddedTime>2018-05-25T08:00:00</AddedTime>
      <UnixAddedTime>1527235200</UnixAddedTime>
      <LastUpdate>2018-05-25T08:00:00</LastUpdate>
      <UnixLastUpdate>1527235200</UnixLastUpdate>
      <TimeoutInMinutes>15</TimeoutInMinutes>
      <Platform>Sandbox</Platform>
      <Pair>
        <PrimaryCurrency>BTS</PrimaryCurrency>
        <SecondaryCurrency>BTC</SecondaryCurrency>
      </Pair>
    </BaseOrder>
    <BaseOrder xsi:type="ExchangeOrder">
      <OrderId>ff0f1a4d-9122-43fb-bf61-5204f476359d</OrderId>
      <OrderStatus>Completed</OrderStatus>
      <OrderStatusAsString>Completed</OrderStatusAsString>
      <OrderType>Sell</OrderType>
      <OrderTypeAsString>Sell</OrderTypeAsString>
      <PriceType>Limit</PriceType>
      <PriceTypeAsString>Limit</PriceTypeAsString>
      <Amount>1000</Amount>
      <AmountFilled>0.0</AmountFilled>
      <Price>0.0000265</Price>
      <FeePercentage>0.1</FeePercentage>
      <FeeCosts>0.00002650</FeeCosts>
      <Profits>-0.0001000</Profits>
      <Notes />
      <Origin />
      <DependsOn />
      <IsExecutingAsId />
      <AddedTime>2018-05-25T13:10:00</AddedTime>
      <UnixAddedTime>1527253800</UnixAddedTime>
      <LastUpdate>2018-05-25T13:10:00</LastUpdate>
      <UnixLastUpdate>1527253800</UnixLastUpdate>
      <TimeoutInMinutes>15</TimeoutInMinutes>
      <Platform>Sandbox</Platform>
      <Pair>
        <PrimaryCurrency>BTS</PrimaryCurrency>
        <SecondaryCurrency>BTC</SecondaryCurrency>
      </Pair>
    </BaseOrder>
    <BaseOrder xsi:type="ExchangeOrder">
      <OrderId>64aad065-cfb3-4e67-b7f5-a2e389dd8dbf</OrderId>
      <OrderStatus>Completed</OrderStatus>
      <OrderStatusAsString>Completed</OrderStatusAsString>
      <OrderType>Buy</OrderType>
      <OrderTypeAsString>Buy</OrderTypeAsString>
      <PriceType>Limit</PriceType>
      <PriceTypeAsString>Limit</PriceTypeAsString>
      <Amount>1000</Amount>
      <AmountFilled>0.0</AmountFilled>
      <Price>0.0000262</Price>
      <FeePercentage>0.1</FeePercentage>
      <FeeCosts>0.00002620</FeeCosts>
      <Profits>0.0</Profits>
      <Notes />
      <Origin />
      <DependsOn />
      <IsExecutingAsId />
      <AddedTime>2018-05-25T17:15:00</AddedTime>
      <UnixAddedTime>1527268500</UnixAddedTime>
      <LastUpdate>2018-05-25T17:15:00</LastUpdate>
      <UnixLastUpdate>1527268500</UnixLastUpdate>
      <TimeoutInMinutes>15</TimeoutInMinutes>
      <Platform>Sandbox</Platform>
      <Pair>
        <PrimaryCurrency>BTS</PrimaryCurrency>
        <SecondaryCurrency>BTC</SecondaryCurrency>
      </Pair>
    </BaseOrder>
    <BaseOrder xsi:type="ExchangeOrder">
      <OrderId>321dce29-c556-4671-9d1d-e5f49e5eaa82</OrderId>
      <OrderStatus>Completed</OrderStatus>
      <OrderStatusAsString>Completed</OrderStatusAsString>
      <OrderType>Sell</OrderType>
      <OrderTypeAsString>Sell</OrderTypeAsString>
      <PriceType>Limit</PriceType>
      <PriceTypeAsString>Limit</PriceTypeAsString>
      <Amount>1000</Amount>
      <AmountFilled>0.0</AmountFilled>
      <Price>0.00002585</Price>
      <FeePercentage>0.1</FeePercentage>
      <FeeCosts>0.000025850</FeeCosts>
      <Profits>-0.00035000</Profits>
      <Notes />
      <Origin />
      <DependsOn />
      <IsExecutingAsId />
      <AddedTime>2018-05-26T00:40:00</AddedTime>
      <UnixAddedTime>1527295200</UnixAddedTime>
      <LastUpdate>2018-05-26T00:40:00</LastUpdate>
      <UnixLastUpdate>1527295200</UnixLastUpdate>
      <TimeoutInMinutes>15</TimeoutInMinutes>
      <Platform>Sandbox</Platform>
      <Pair>
        <PrimaryCurrency>BTS</PrimaryCurrency>
        <SecondaryCurrency>BTC</SecondaryCurrency>
      </Pair>
    </BaseOrder>
    <BaseOrder xsi:type="ExchangeOrder">
      <OrderId>bd46b5d1-3a53-4423-a4e2-242ad81f080e</OrderId>
      <OrderStatus>Completed</OrderStatus>
      <OrderStatusAsString>Completed</OrderStatusAsString>
      <OrderType>Buy</OrderType>
      <OrderTypeAsString>Buy</OrderTypeAsString>
      <PriceType>Limit</PriceType>
      <PriceTypeAsString>Limit</PriceTypeAsString>
      <Amount>1000</Amount>
      <AmountFilled>0.0</AmountFilled>
      <Price>0.00002608</Price>
      <FeePercentage>0.1</FeePercentage>
      <FeeCosts>0.000026080</FeeCosts>
      <Profits>0.0</Profits>
      <Notes />
      <Origin />
      <DependsOn />
      <IsExecutingAsId />
      <AddedTime>2018-05-26T05:05:00</AddedTime>
      <UnixAddedTime>1527311100</UnixAddedTime>
      <LastUpdate>2018-05-26T05:05:00</LastUpdate>
      <UnixLastUpdate>1527311100</UnixLastUpdate>
      <TimeoutInMinutes>15</TimeoutInMinutes>
      <Platform>Sandbox</Platform>
      <Pair>
        <PrimaryCurrency>BTS</PrimaryCurrency>
        <SecondaryCurrency>BTC</SecondaryCurrency>
      </Pair>
    </BaseOrder>
    <BaseOrder xsi:type="ExchangeOrder">
      <OrderId>b2136ca6-92a5-47dd-bfc1-45b6a25ce6ad</OrderId>
      <OrderStatus>Completed</OrderStatus>
      <OrderStatusAsString>Completed</OrderStatusAsString>
      <OrderType>Sell</OrderType>
      <OrderTypeAsString>Sell</OrderTypeAsString>
      <PriceType>Limit</PriceType>
      <PriceTypeAsString>Limit</PriceTypeAsString>
      <Amount>1000</Amount>
      <AmountFilled>0.0</AmountFilled>
      <Price>0.00002611</Price>
      <FeePercentage>0.1</FeePercentage>
      <FeeCosts>0.000026110</FeeCosts>
      <Profits>0.00003000</Profits>
      <Notes />
      <Origin />
      <DependsOn />
      <IsExecutingAsId />
      <AddedTime>2018-05-26T06:50:00</AddedTime>
      <UnixAddedTime>1527317400</UnixAddedTime>
      <LastUpdate>2018-05-26T06:50:00</LastUpdate>
      <UnixLastUpdate>1527317400</UnixLastUpdate>
      <TimeoutInMinutes>15</TimeoutInMinutes>
      <Platform>Sandbox</Platform>
      <Pair>
        <PrimaryCurrency>BTS</PrimaryCurrency>
        <SecondaryCurrency>BTC</SecondaryCurrency>
      </Pair>
    </BaseOrder>
    <BaseOrder xsi:type="ExchangeOrder">
      <OrderId>085e9b01-f5fd-4fa0-bf1b-03f07679ff81</OrderId>
      <OrderStatus>Completed</OrderStatus>
      <OrderStatusAsString>Completed</OrderStatusAsString>
      <OrderType>Buy</OrderType>
      <OrderTypeAsString>Buy</OrderTypeAsString>
      <PriceType>Limit</PriceType>
      <PriceTypeAsString>Limit</PriceTypeAsString>
      <Amount>1000</Amount>
      <AmountFilled>0.0</AmountFilled>
      <Price>0.00002643</Price>
      <FeePercentage>0.1</FeePercentage>
      <FeeCosts>0.000026430</FeeCosts>
      <Profits>0.0</Profits>
      <Notes />
      <Origin />
      <DependsOn />
      <IsExecutingAsId />
      <AddedTime>2018-05-26T12:05:00</AddedTime>
      <UnixAddedTime>1527336300</UnixAddedTime>
      <LastUpdate>2018-05-26T12:05:00</LastUpdate>
      <UnixLastUpdate>1527336300</UnixLastUpdate>
      <TimeoutInMinutes>15</TimeoutInMinutes>
      <Platform>Sandbox</Platform>
      <Pair>
        <PrimaryCurrency>BTS</PrimaryCurrency>
        <SecondaryCurrency>BTC</SecondaryCurrency>
      </Pair>
    </BaseOrder>
    <BaseOrder xsi:type="ExchangeOrder">
      <OrderId>a1ec1c5c-5632-4e02-a13f-efb0ee94f261</OrderId>
      <OrderStatus>Completed</OrderStatus>
      <OrderStatusAsString>Completed</OrderStatusAsString>
      <OrderType>Sell</OrderType>
      <OrderTypeAsString>Sell</OrderTypeAsString>
      <PriceType>Limit</PriceType>
      <PriceTypeAsString>Limit</PriceTypeAsString>
      <Amount>1000</Amount>
      <AmountFilled>0.0</AmountFilled>
      <Price>0.00002658</Price>
      <FeePercentage>0.1</FeePercentage>
      <FeeCosts>0.000026580</FeeCosts>
      <Profits>0.00015000</Profits>
      <Notes />
      <Origin />
      <DependsOn />
      <IsExecutingAsId />
      <AddedTime>2018-05-26T17:10:00</AddedTime>
      <UnixAddedTime>1527354600</UnixAddedTime>
      <LastUpdate>2018-05-26T17:10:00</LastUpdate>
      <UnixLastUpdate>1527354600</UnixLastUpdate>
      <TimeoutInMinutes>15</TimeoutInMinutes>
      <Platform>Sandbox</Platform>
      <Pair>
        <PrimaryCurrency>BTS</PrimaryCurrency>
        <SecondaryCurrency>BTC</SecondaryCurrency>
      </Pair>
    </BaseOrder>
    <BaseOrder xsi:type="ExchangeOrder">
      <OrderId>07a477cc-2cc0-4892-8d2d-ced415d783bb</OrderId>
      <OrderStatus>Completed</OrderStatus>
      <OrderStatusAsString>Completed</OrderStatusAsString>
      <OrderType>Buy</OrderType>
      <OrderTypeAsString>Buy</OrderTypeAsString>
      <PriceType>Limit</PriceType>
      <PriceTypeAsString>Limit</PriceTypeAsString>
      <Amount>1000</Amount>
      <AmountFilled>0.0</AmountFilled>
      <Price>0.00002688</Price>
      <FeePercentage>0.1</FeePercentage>
      <FeeCosts>0.000026880</FeeCosts>
      <Profits>0.0</Profits>
      <Notes />
      <Origin />
      <DependsOn />
      <IsExecutingAsId />
      <AddedTime>2018-05-26T23:00:00.0003929Z</AddedTime>
      <UnixAddedTime>1527375600</UnixAddedTime>
      <LastUpdate>2018-05-26T23:00:00.0003929Z</LastUpdate>
      <UnixLastUpdate>1527375600</UnixLastUpdate>
      <TimeoutInMinutes>15</TimeoutInMinutes>
      <Platform>Sandbox</Platform>
      <Pair>
        <PrimaryCurrency>BTS</PrimaryCurrency>
        <SecondaryCurrency>BTC</SecondaryCurrency>
      </Pair>
    </BaseOrder>
    <BaseOrder xsi:type="ExchangeOrder">
      <OrderId>5e9c7231-b8c3-4225-8622-80d287b423d9</OrderId>
      <OrderStatus>Completed</OrderStatus>
      <OrderStatusAsString>Completed</OrderStatusAsString>
      <OrderType>Sell</OrderType>
      <OrderTypeAsString>Sell</OrderTypeAsString>
      <PriceType>Limit</PriceType>
      <PriceTypeAsString>Limit</PriceTypeAsString>
      <Amount>1000</Amount>
      <AmountFilled>0.0</AmountFilled>
      <Price>0.00002687</Price>
      <FeePercentage>0.1</FeePercentage>
      <FeeCosts>0.000026870</FeeCosts>
      <Profits>-0.00001000</Profits>
      <Notes />
      <Origin />
      <DependsOn />
      <IsExecutingAsId />
      <AddedTime>2018-05-26T23:45:00</AddedTime>
      <UnixAddedTime>1527378300</UnixAddedTime>
      <LastUpdate>2018-05-26T23:45:00</LastUpdate>
      <UnixLastUpdate>1527378300</UnixLastUpdate>
      <TimeoutInMinutes>15</TimeoutInMinutes>
      <Platform>Sandbox</Platform>
      <Pair>
        <PrimaryCurrency>BTS</PrimaryCurrency>
        <SecondaryCurrency>BTC</SecondaryCurrency>
      </Pair>
    </BaseOrder>
    <BaseOrder xsi:type="ExchangeOrder">
      <OrderId>7eda2fba-8689-4280-9bdd-5360e0e5cf5e</OrderId>
      <OrderStatus>Completed</OrderStatus>
      <OrderStatusAsString>Completed</OrderStatusAsString>
      <OrderType>Buy</OrderType>
      <OrderTypeAsString>Buy</OrderTypeAsString>
      <PriceType>Limit</PriceType>
      <PriceTypeAsString>Limit</PriceTypeAsString>
      <Amount>1000</Amount>
      <AmountFilled>0.0</AmountFilled>
      <Price>0.00002690</Price>
      <FeePercentage>0.1</FeePercentage>
      <FeeCosts>0.000026900</FeeCosts>
      <Profits>0.0</Profits>
      <Notes />
      <Origin />
      <DependsOn />
      <IsExecutingAsId />
      <AddedTime>2018-05-27T07:45:00</AddedTime>
      <UnixAddedTime>1527407100</UnixAddedTime>
      <LastUpdate>2018-05-27T07:45:00</LastUpdate>
      <UnixLastUpdate>1527407100</UnixLastUpdate>
      <TimeoutInMinutes>15</TimeoutInMinutes>
      <Platform>Sandbox</Platform>
      <Pair>
        <PrimaryCurrency>BTS</PrimaryCurrency>
        <SecondaryCurrency>BTC</SecondaryCurrency>
      </Pair>
    </BaseOrder>
    <BaseOrder xsi:type="ExchangeOrder">
      <OrderId>b67f4da6-ef2d-4b4d-80b4-dc0d1bed604b</OrderId>
      <OrderStatus>Completed</OrderStatus>
      <OrderStatusAsString>Completed</OrderStatusAsString>
      <OrderType>Sell</OrderType>
      <OrderTypeAsString>Sell</OrderTypeAsString>
      <PriceType>Limit</PriceType>
      <PriceTypeAsString>Limit</PriceTypeAsString>
      <Amount>1000</Amount>
      <AmountFilled>0.0</AmountFilled>
      <Price>0.00002684</Price>
      <FeePercentage>0.1</FeePercentage>
      <FeeCosts>0.000026840</FeeCosts>
      <Profits>-0.00006000</Profits>
      <Notes />
      <Origin />
      <DependsOn />
      <IsExecutingAsId />
      <AddedTime>2018-05-27T10:35:00</AddedTime>
      <UnixAddedTime>1527417300</UnixAddedTime>
      <LastUpdate>2018-05-27T10:35:00</LastUpdate>
      <UnixLastUpdate>1527417300</UnixLastUpdate>
      <TimeoutInMinutes>15</TimeoutInMinutes>
      <Platform>Sandbox</Platform>
      <Pair>
        <PrimaryCurrency>BTS</PrimaryCurrency>
        <SecondaryCurrency>BTC</SecondaryCurrency>
      </Pair>
    </BaseOrder>
    <BaseOrder xsi:type="ExchangeOrder">
      <OrderId>ef8f01c1-2acb-4742-8553-7554861cacc3</OrderId>
      <OrderStatus>Completed</OrderStatus>
      <OrderStatusAsString>Completed</OrderStatusAsString>
      <OrderType>Buy</OrderType>
      <OrderTypeAsString>Buy</OrderTypeAsString>
      <PriceType>Limit</PriceType>
      <PriceTypeAsString>Limit</PriceTypeAsString>
      <Amount>1000</Amount>
      <AmountFilled>0.0</AmountFilled>
      <Price>0.00002692</Price>
      <FeePercentage>0.1</FeePercentage>
      <FeeCosts>0.000026920</FeeCosts>
      <Profits>0.0</Profits>
      <Notes />
      <Origin />
      <DependsOn />
      <IsExecutingAsId />
      <AddedTime>2018-05-27T14:05:00</AddedTime>
      <UnixAddedTime>1527429900</UnixAddedTime>
      <LastUpdate>2018-05-27T14:05:00</LastUpdate>
      <UnixLastUpdate>1527429900</UnixLastUpdate>
      <TimeoutInMinutes>15</TimeoutInMinutes>
      <Platform>Sandbox</Platform>
      <Pair>
        <PrimaryCurrency>BTS</PrimaryCurrency>
        <SecondaryCurrency>BTC</SecondaryCurrency>
      </Pair>
    </BaseOrder>
    <BaseOrder xsi:type="ExchangeOrder">
      <OrderId>551c8b1b-38f1-4e65-b39e-9f4bdd2263a6</OrderId>
      <OrderStatus>Completed</OrderStatus>
      <OrderStatusAsString>Completed</OrderStatusAsString>
      <OrderType>Sell</OrderType>
      <OrderTypeAsString>Sell</OrderTypeAsString>
      <PriceType>Limit</PriceType>
      <PriceTypeAsString>Limit</PriceTypeAsString>
      <Amount>1000</Amount>
      <AmountFilled>0.0</AmountFilled>
      <Price>0.00002749</Price>
      <FeePercentage>0.1</FeePercentage>
      <FeeCosts>0.000027490</FeeCosts>
      <Profits>0.00057000</Profits>
      <Notes />
      <Origin />
      <DependsOn />
      <IsExecutingAsId />
      <AddedTime>2018-05-27T16:45:00</AddedTime>
      <UnixAddedTime>1527439500</UnixAddedTime>
      <LastUpdate>2018-05-27T16:45:00</LastUpdate>
      <UnixLastUpdate>1527439500</UnixLastUpdate>
      <TimeoutInMinutes>15</TimeoutInMinutes>
      <Platform>Sandbox</Platform>
      <Pair>
        <PrimaryCurrency>BTS</PrimaryCurrency>
        <SecondaryCurrency>BTC</SecondaryCurrency>
      </Pair>
    </BaseOrder>
    <BaseOrder xsi:type="ExchangeOrder">
      <OrderId>354443d3-24a6-4e24-a02b-3f1dbe399549</OrderId>
      <OrderStatus>Completed</OrderStatus>
      <OrderStatusAsString>Completed</OrderStatusAsString>
      <OrderType>Buy</OrderType>
      <OrderTypeAsString>Buy</OrderTypeAsString>
      <PriceType>Limit</PriceType>
      <PriceTypeAsString>Limit</PriceTypeAsString>
      <Amount>1000</Amount>
      <AmountFilled>0.0</AmountFilled>
      <Price>0.00002737</Price>
      <FeePercentage>0.1</FeePercentage>
      <FeeCosts>0.000027370</FeeCosts>
      <Profits>0.0</Profits>
      <Notes />
      <Origin />
      <DependsOn />
      <IsExecutingAsId />
      <AddedTime>2018-05-27T22:15:00</AddedTime>
      <UnixAddedTime>1527459300</UnixAddedTime>
      <LastUpdate>2018-05-27T22:15:00</LastUpdate>
      <UnixLastUpdate>1527459300</UnixLastUpdate>
      <TimeoutInMinutes>15</TimeoutInMinutes>
      <Platform>Sandbox</Platform>
      <Pair>
        <PrimaryCurrency>BTS</PrimaryCurrency>
        <SecondaryCurrency>BTC</SecondaryCurrency>
      </Pair>
    </BaseOrder>
  </CompletedOrders>
  <IsOrderStopLossActive>false</IsOrderStopLossActive>
  <PlatformType>SpotTrading</PlatformType>
  <CoinPosition>Sold</CoinPosition>
  <FundsPosition>NoPosition</FundsPosition>
  <CurrentTradeAmount>1000</CurrentTradeAmount>
  <CorrectedTradeAmount>0.0</CorrectedTradeAmount>
  <LastBuyPrice>0.00002737</LastBuyPrice>
  <LastSellPrice>0.00002749</LastSellPrice>
  <CappedSeconds>5</CappedSeconds>
  <Interval>5</Interval>
  <StopLoss>0</StopLoss>
  <StopLossPrice>0.0000291258</StopLossPrice>
  <DisableAfterStopLoss>false</DisableAfterStopLoss>
  <PriceChangeToBuy>0</PriceChangeToBuy>
  <PriceChangeToSell>0</PriceChangeToSell>
  <PriceChangeTarget>0.0000420</PriceChangeTarget>
  <Macd>
    <IndicatorType>Aroon</IndicatorType>
    <PriceMarket>
      <PrimaryCurrency>BTC</PrimaryCurrency>
      <SecondaryCurrency>DEMO1</SecondaryCurrency>
      <ContractName />
      <PriceSource>Sandbox</PriceSource>
      <PriceMarketType>Forex</PriceMarketType>
    </PriceMarket>
    <ChartType>CandlestickHLC</ChartType>
    <Timer>5</Timer>
    <ChartStepping>1.0</ChartStepping>
    <Deviation>0</Deviation>
    <StandAlone>false</StandAlone>
    <InBenchmark>false</InBenchmark>
    <BetaStage>false</BetaStage>
    <UseBuySignals>true</UseBuySignals>
    <UseSellSignals>true</UseSellSignals>
    <UseLongSignals>true</UseLongSignals>
    <UseNoPositionSignals>true</UseNoPositionSignals>
    <UseShortSignals>true</UseShortSignals>
    <ReverseSignals>false</ReverseSignals>
    <BuySellResult>Sell</BuySellResult>
    <ShortLongResult>NoPosition</ShortLongResult>
    <MappedLongSignal>Long</MappedLongSignal>
    <MappedShortSignal>Short</MappedShortSignal>
    <IndicatorInterface>
      <IndicatorField>
        <Title>MACD Fast</Title>
        <FieldType>number</FieldType>
        <Min>0</Min>
        <Max>500</Max>
        <Pattern>[0-9]+</Pattern>
        <Step>1</Step>
        <Value>6</Value>
      </IndicatorField>
      <IndicatorField>
        <Title>MACD Slow</Title>
        <FieldType>number</FieldType>
        <Min>0</Min>
        <Max>500</Max>
        <Pattern>[0-9]+</Pattern>
        <Step>1</Step>
        <Value>400</Value>
      </IndicatorField>
      <IndicatorField>
        <Title>MACD Signal</Title>
        <FieldType>number</FieldType>
        <Min>0</Min>
        <Max>500</Max>
        <Pattern>[0-9]+</Pattern>
        <Step>1</Step>
        <Value>41</Value>
      </IndicatorField>
    </IndicatorInterface>
    <MacdFast>6</MacdFast>
    <MacdSlow>400</MacdSlow>
    <MacdSign>41</MacdSign>
    <SupportedBotTypes>
      <enumBotType>TradeBot</enumBotType>
      <enumBotType>MarginBot</enumBotType>
      <enumBotType>LeverageBot</enumBotType>
    </SupportedBotTypes>
  </Macd>
  <BBands>
    <IndicatorType>Aroon</IndicatorType>
    <PriceMarket>
      <PrimaryCurrency>BTC</PrimaryCurrency>
      <SecondaryCurrency>DEMO1</SecondaryCurrency>
      <ContractName />
      <PriceSource>Sandbox</PriceSource>
      <PriceMarketType>Forex</PriceMarketType>
    </PriceMarket>
    <ChartType>CandlestickHLC</ChartType>
    <Timer>5</Timer>
    <ChartStepping>1.0</ChartStepping>
    <Deviation>0</Deviation>
    <StandAlone>false</StandAlone>
    <InBenchmark>false</InBenchmark>
    <BetaStage>false</BetaStage>
    <UseBuySignals>true</UseBuySignals>
    <UseSellSignals>true</UseSellSignals>
    <UseLongSignals>true</UseLongSignals>
    <UseNoPositionSignals>true</UseNoPositionSignals>
    <UseShortSignals>true</UseShortSignals>
    <ReverseSignals>false</ReverseSignals>
    <BuySellResult>Stay</BuySellResult>
    <ShortLongResult>NoPosition</ShortLongResult>
    <MappedLongSignal>Long</MappedLongSignal>
    <MappedShortSignal>Short</MappedShortSignal>
    <IndicatorInterface>
      <IndicatorField>
        <Title>Length</Title>
        <FieldType>number</FieldType>
        <Min>1</Min>
        <Max>999999</Max>
        <Pattern>[0-9]+</Pattern>
        <Step>1</Step>
        <Value>62</Value>
      </IndicatorField>
      <IndicatorField>
        <Title>Dev.Up</Title>
        <FieldType>number</FieldType>
        <Min>0.00001</Min>
        <Max>999.9</Max>
        <Pattern>[0-9]+([.\,][0-9]{1,2})?</Pattern>
        <Step>0.01</Step>
        <Value>0.51</Value>
      </IndicatorField>
      <IndicatorField>
        <Title>Dev.Down</Title>
        <FieldType>number</FieldType>
        <Min>0.00001</Min>
        <Max>999.9</Max>
        <Pattern>[0-9]+([.\,][0-9]{1,2})?</Pattern>
        <Step>0.01</Step>
        <Value>1.15</Value>
      </IndicatorField>
      <IndicatorField>
        <Title>MA Type</Title>
        <FieldType>optionlist</FieldType>
        <Min>0.0</Min>
        <Max>0.0</Max>
        <Pattern />
        <Step>0.0</Step>
        <Value>Wma</Value>
        <Options>
          <string>Sma</string>
          <string>Ema</string>
          <string>Wma</string>
          <string>Dema</string>
          <string>Tema</string>
          <string>Trima</string>
          <string>Kama</string>
          <string>Mama</string>
          <string>T3</string>
        </Options>
      </IndicatorField>
      <IndicatorField>
        <Title>Deviation</Title>
        <FieldType>number</FieldType>
        <Min>0</Min>
        <Max>999999</Max>
        <Pattern>[0-9]+</Pattern>
        <Step>1</Step>
        <Value>0</Value>
      </IndicatorField>
      <IndicatorField>
        <Title>Require FCC</Title>
        <FieldType>boolean</FieldType>
        <Min>0.0</Min>
        <Max>0.0</Max>
        <Pattern />
        <Step>0.0</Step>
        <Value>False</Value>
      </IndicatorField>
      <IndicatorField>
        <Title>Reset Middle</Title>
        <FieldType>boolean</FieldType>
        <Min>0.0</Min>
        <Max>0.0</Max>
        <Pattern />
        <Step>0.0</Step>
        <Value>False</Value>
      </IndicatorField>
      <IndicatorField>
        <Title>Allow Mid Sells</Title>
        <FieldType>boolean</FieldType>
        <Min>0.0</Min>
        <Max>0.0</Max>
        <Pattern />
        <Step>0.0</Step>
        <Value>False</Value>
      </IndicatorField>
    </IndicatorInterface>
    <Length>62</Length>
    <Devup>0.51</Devup>
    <Devdn>1.15</Devdn>
    <MaType>Wma</MaType>
    <ResetMid>false</ResetMid>
    <AllowMidSell>false</AllowMidSell>
    <RequireFcc>false</RequireFcc>
    <SupportedBotTypes>
      <enumBotType>TradeBot</enumBotType>
      <enumBotType>MarginBot</enumBotType>
      <enumBotType>LeverageBot</enumBotType>
    </SupportedBotTypes>
  </BBands>
  <Rsi>
    <IndicatorType>Aroon</IndicatorType>
    <PriceMarket>
      <PrimaryCurrency>BTC</PrimaryCurrency>
      <SecondaryCurrency>DEMO1</SecondaryCurrency>
      <ContractName />
      <PriceSource>Sandbox</PriceSource>
      <PriceMarketType>Forex</PriceMarketType>
    </PriceMarket>
    <ChartType>CandlestickHLC</ChartType>
    <Timer>5</Timer>
    <ChartStepping>1.0</ChartStepping>
    <Deviation>0</Deviation>
    <StandAlone>false</StandAlone>
    <InBenchmark>false</InBenchmark>
    <BetaStage>false</BetaStage>
    <UseBuySignals>true</UseBuySignals>
    <UseSellSignals>true</UseSellSignals>
    <UseLongSignals>true</UseLongSignals>
    <UseNoPositionSignals>true</UseNoPositionSignals>
    <UseShortSignals>true</UseShortSignals>
    <ReverseSignals>false</ReverseSignals>
    <BuySellResult>Stay</BuySellResult>
    <ShortLongResult>NoPosition</ShortLongResult>
    <MappedLongSignal>Long</MappedLongSignal>
    <MappedShortSignal>Short</MappedShortSignal>
    <IndicatorInterface>
      <IndicatorField>
        <Title>Length</Title>
        <FieldType>number</FieldType>
        <Min>1</Min>
        <Max>999999</Max>
        <Pattern>[0-9]+</Pattern>
        <Step>1</Step>
        <Value>18</Value>
      </IndicatorField>
      <IndicatorField>
        <Title>Buy level</Title>
        <FieldType>number</FieldType>
        <Min>0</Min>
        <Max>100</Max>
        <Pattern>[0-9]+([.\,][0-9]{1,1})?</Pattern>
        <Step>0.1</Step>
        <Value>28</Value>
      </IndicatorField>
      <IndicatorField>
        <Title>Sell level</Title>
        <FieldType>number</FieldType>
        <Min>0</Min>
        <Max>100</Max>
        <Pattern>[0-9]+([.\,][0-9]{1,1})?</Pattern>
        <Step>0.1</Step>
        <Value>83</Value>
      </IndicatorField>
    </IndicatorInterface>
    <RsiLength>18</RsiLength>
    <RsiOversold>28</RsiOversold>
    <RsiOverbought>83</RsiOverbought>
    <Rsi>44.323188413342</Rsi>
    <LastRsi>47.7387088958466</LastRsi>
    <SupportedBotTypes>
      <enumBotType>TradeBot</enumBotType>
      <enumBotType>MarginBot</enumBotType>
      <enumBotType>LeverageBot</enumBotType>
    </SupportedBotTypes>
  </Rsi>
  <UseTwoSignals>true</UseTwoSignals>
</MadHatterBot>